{
  "annotations": {
    "list": [
      {
        "builtIn": 1,
        "datasource": {
          "type": "grafana",
          "uid": "-- Grafana --"
        },
        "enable": true,
        "hide": true,
        "iconColor": "rgba(0, 211, 255, 1)",
        "name": "Annotations & Alerts",
        "type": "dashboard"
      }
    ]
  },
  "editable": true,
  "fiscalYearStartMonth": 0,
  "graphTooltip": 0,
  "id": 1,
  "links": [],
  "panels": [
    {
      "datasource": {
        "type": "prometheus",
        "uid": "cekvp414w9e68e"
      },
      "fieldConfig": {
        "defaults": {
          "color": {
            "mode": "palette-classic"
          },
          "custom": {
            "axisBorderShow": false,
            "axisCenteredZero": false,
            "axisColorMode": "text",
            "axisLabel": "",
            "axisPlacement": "auto",
            "axisSoftMax": 100,
            "axisSoftMin": 0,
            "barAlignment": 0,
            "barWidthFactor": 0.6,
            "drawStyle": "line",
            "fillOpacity": 100,
            "gradientMode": "opacity",
            "hideFrom": {
              "legend": false,
              "tooltip": false,
              "viz": false
            },
            "insertNulls": false,
            "lineInterpolation": "smooth",
            "lineStyle": {
              "dash": [
                10,
                10
              ],
              "fill": "dash"
            },
            "lineWidth": 1,
            "pointSize": 7,
            "scaleDistribution": {
              "type": "linear"
            },
            "showPoints": "auto",
            "spanNulls": false,
            "stacking": {
              "group": "A",
              "mode": "none"
            },
            "thresholdsStyle": {
              "mode": "off"
            }
          },
          "mappings": [],
          "thresholds": {
            "mode": "absolute",
            "steps": [
              {
                "color": "text"
              },
              {
                "color": "red",
                "value": 80
              }
            ]
          }
        },
        "overrides": []
      },
      "gridPos": {
        "h": 7,
        "w": 9,
        "x": 0,
        "y": 0
      },
      "id": 7,
      "options": {
        "legend": {
          "calcs": [],
          "displayMode": "list",
          "placement": "bottom",
          "showLegend": false
        },
        "tooltip": {
          "hideZeros": false,
          "mode": "single",
          "sort": "none"
        }
      },
      "pluginVersion": "11.6.0",
      "targets": [
        {
          "editorMode": "code",
          "expr": "100 - (avg(rate(node_cpu_seconds_total{mode=\"idle\"}[1m])) by (instance) * 100)",
          "legendFormat": "__auto",
          "range": true,
          "refId": "A"
        }
      ],
      "title": "🏿 CPU 사용량 (%)",
      "transparent": true,
      "type": "timeseries"
    },
    {
      "datasource": {
        "type": "prometheus",
        "uid": "cekvp414w9e68e"
      },
      "fieldConfig": {
        "defaults": {
          "color": {
            "mode": "thresholds"
          },
          "mappings": [],
          "thresholds": {
            "mode": "absolute",
            "steps": [
              {
                "color": "green"
              },
              {
                "color": "yellow",
                "value": 60
              },
              {
                "color": "red",
                "value": 80
              }
            ]
          },
          "unit": "percent"
        },
        "overrides": []
      },
      "gridPos": {
        "h": 7,
        "w": 7,
        "x": 9,
        "y": 0
      },
      "id": 3,
      "options": {
        "minVizHeight": 75,
        "minVizWidth": 75,
        "orientation": "auto",
        "reduceOptions": {
          "calcs": [
            "lastNotNull"
          ],
          "fields": "",
          "values": false
        },
        "showThresholdLabels": false,
        "showThresholdMarkers": true,
        "sizing": "auto"
      },
      "pluginVersion": "11.6.0",
      "targets": [
        {
          "editorMode": "code",
          "expr": "(node_memory_MemTotal_bytes - node_memory_MemFree_bytes) / node_memory_MemTotal_bytes * 100\r\n",
          "legendFormat": "__auto",
          "range": true,
          "refId": "A"
        }
      ],
      "title": "💾 메모리 사용률 ",
      "transparent": true,
      "type": "gauge"
    },
    {
      "datasource": {
        "type": "prometheus",
        "uid": "cekvp414w9e68e"
      },
      "fieldConfig": {
        "defaults": {
          "color": {
            "mode": "palette-classic"
          },
          "custom": {
            "axisBorderShow": false,
            "axisCenteredZero": false,
            "axisColorMode": "text",
            "axisLabel": "",
            "axisPlacement": "auto",
            "axisSoftMax": 100,
            "axisSoftMin": 0,
            "fillOpacity": 0,
            "gradientMode": "none",
            "hideFrom": {
              "legend": false,
              "tooltip": false,
              "viz": false
            },
            "lineWidth": 1,
            "scaleDistribution": {
              "type": "linear"
            },
            "thresholdsStyle": {
              "mode": "dashed+area"
            }
          },
          "fieldMinMax": false,
          "mappings": [],
          "thresholds": {
            "mode": "absolute",
            "steps": [
              {
                "color": "text"
              },
              {
                "color": "red",
                "value": 80
              }
            ]
          }
        },
        "overrides": []
      },
      "gridPos": {
        "h": 7,
        "w": 8,
        "x": 16,
        "y": 0
      },
      "id": 6,
      "options": {
        "barRadius": 0.15,
        "barWidth": 1,
        "fullHighlight": true,
        "groupWidth": 0.7,
        "legend": {
          "calcs": [],
          "displayMode": "list",
          "placement": "bottom",
          "showLegend": false
        },
        "orientation": "auto",
        "showValue": "auto",
        "stacking": "none",
        "tooltip": {
          "hideZeros": false,
          "mode": "single",
          "sort": "none"
        },
        "xField": "Time",
        "xTickLabelRotation": 0,
        "xTickLabelSpacing": 100
      },
      "pluginVersion": "11.6.0",
      "targets": [
        {
          "editorMode": "code",
          "expr": "(1 - (sum(node_filesystem_free_bytes{fstype=\"ext4\"}) / sum(node_filesystem_size_bytes{fstype=\"ext4\"}))) * 100",
          "legendFormat": "__auto",
          "range": true,
          "refId": "A"
        }
      ],
      "title": "💿 디스크 사용률 ",
      "transparent": true,
      "type": "barchart"
    },
    {
      "datasource": {
        "type": "prometheus",
        "uid": "cekvp414w9e68e"
      },
      "description": "미디어 서버에 송출하고 있는 카메라 기기 갯수",
      "fieldConfig": {
        "defaults": {
          "color": {
            "mode": "continuous-blues"
          },
          "fieldMinMax": false,
          "mappings": [
            {
              "options": {
                "0": {
                  "color": "semi-dark-red",
                  "index": 0,
                  "text": "No Producer"
                }
              },
              "type": "value"
            },
            {
              "options": {
                "match": "null+nan",
                "result": {
                  "color": "yellow",
                  "index": 1,
                  "text": "Error"
                }
              },
              "type": "special"
            }
          ],
          "thresholds": {
            "mode": "absolute",
            "steps": [
              {
                "color": "green"
              },
              {
                "color": "red",
                "value": 80
              }
            ]
          }
        },
        "overrides": []
      },
      "gridPos": {
        "h": 8,
        "w": 12,
        "x": 0,
        "y": 7
      },
      "id": 1,
      "options": {
        "minVizHeight": 75,
        "minVizWidth": 75,
        "orientation": "auto",
        "reduceOptions": {
          "calcs": [
            "lastNotNull"
          ],
          "fields": "",
          "values": false
        },
        "showThresholdLabels": false,
        "showThresholdMarkers": false,
        "sizing": "auto"
      },
      "pluginVersion": "11.6.0",
      "targets": [
        {
          "datasource": {
            "type": "prometheus",
            "uid": "cekvp414w9e68e"
          },
          "disableTextWrap": false,
          "editorMode": "builder",
          "exemplar": false,
          "expr": "active_producers",
          "fullMetaSearch": false,
          "hide": false,
          "includeNullMetadata": true,
          "instant": false,
          "legendFormat": "producer",
          "range": true,
          "refId": "producer",
          "useBackend": false
        }
      ],
      "title": "📷 현재 접속자 현황 (송출자)",
      "transparent": true,
      "type": "gauge"
    },
    {
      "datasource": {
        "type": "prometheus",
        "uid": "cekvp414w9e68e"
      },
      "description": "미디어 서버에 스트리밍을 요청하는 클라언트 수 ",
      "fieldConfig": {
        "defaults": {
          "color": {
            "mode": "continuous-YlBl"
          },
          "fieldMinMax": false,
          "mappings": [
            {
              "options": {
                "0": {
                  "color": "semi-dark-red",
                  "index": 0,
                  "text": "No Consumer"
                }
              },
              "type": "value"
            },
            {
              "options": {
                "match": "null+nan",
                "result": {
                  "color": "yellow",
                  "index": 1,
                  "text": "Error"
                }
              },
              "type": "special"
            }
          ],
          "thresholds": {
            "mode": "absolute",
            "steps": [
              {
                "color": "green"
              },
              {
                "color": "red",
                "value": 80
              }
            ]
          }
        },
        "overrides": []
      },
      "gridPos": {
        "h": 8,
        "w": 12,
        "x": 12,
        "y": 7
      },
      "id": 2,
      "options": {
        "minVizHeight": 75,
        "minVizWidth": 75,
        "orientation": "auto",
        "reduceOptions": {
          "calcs": [
            "lastNotNull"
          ],
          "fields": "",
          "values": false
        },
        "showThresholdLabels": false,
        "showThresholdMarkers": false,
        "sizing": "auto"
      },
      "pluginVersion": "11.6.0",
      "targets": [
        {
          "datasource": {
            "type": "prometheus",
            "uid": "cekvp414w9e68e"
          },
          "disableTextWrap": false,
          "editorMode": "builder",
          "exemplar": false,
          "expr": "active_consumers",
          "fullMetaSearch": false,
          "hide": false,
          "includeNullMetadata": true,
          "instant": false,
          "legendFormat": "consumer",
          "range": true,
          "refId": "consumer",
          "useBackend": false
        }
      ],
      "title": "📱 현재 접속자 현황 (송신자)",
      "transparent": true,
      "type": "gauge"
    },
    {
      "datasource": {
        "type": "prometheus",
        "uid": "cekvp414w9e68e"
      },
      "description": "초당 수신 바이트 ",
      "fieldConfig": {
        "defaults": {
          "color": {
            "mode": "palette-classic"
          },
          "custom": {
            "axisBorderShow": false,
            "axisCenteredZero": false,
            "axisColorMode": "text",
            "axisLabel": "",
            "axisPlacement": "auto",
            "barAlignment": 0,
            "barWidthFactor": 0.6,
            "drawStyle": "line",
            "fillOpacity": 0,
            "gradientMode": "none",
            "hideFrom": {
              "legend": false,
              "tooltip": false,
              "viz": false
            },
            "insertNulls": false,
            "lineInterpolation": "linear",
            "lineWidth": 1,
            "pointSize": 5,
            "scaleDistribution": {
              "type": "linear"
            },
            "showPoints": "auto",
            "spanNulls": false,
            "stacking": {
              "group": "A",
              "mode": "none"
            },
            "thresholdsStyle": {
              "mode": "off"
            }
          },
          "mappings": [],
          "thresholds": {
            "mode": "absolute",
            "steps": [
              {
                "color": "green"
              },
              {
                "color": "red",
                "value": 20000
              }
            ]
          }
        },
        "overrides": []
      },
      "gridPos": {
        "h": 8,
        "w": 12,
        "x": 0,
        "y": 15
      },
      "id": 4,
      "options": {
        "legend": {
          "calcs": [],
          "displayMode": "list",
          "placement": "bottom",
          "showLegend": true
        },
        "tooltip": {
          "hideZeros": false,
          "mode": "single",
          "sort": "none"
        }
      },
      "pluginVersion": "11.6.0",
      "targets": [
        {
          "editorMode": "code",
          "expr": "rate(node_network_transmit_bytes_total{device!=\"lo\"}[1m])",
          "hide": false,
          "legendFormat": "송신",
          "range": true,
          "refId": "송신"
        },
        {
          "datasource": {
            "type": "prometheus",
            "uid": "cekvp414w9e68e"
          },
          "editorMode": "code",
          "expr": "rate(node_network_receive_bytes_total{device!=\"lo\"}[1m])\r\n",
          "hide": false,
          "instant": false,
          "legendFormat": "수신",
          "range": true,
          "refId": "수"
        },
        {
          "datasource": {
            "type": "prometheus",
            "uid": "cekvp414w9e68e"
          },
          "editorMode": "code",
          "expr": "rate(node_network_receive_bytes_total{device!=\"lo\"}[1m]) + rate(node_network_transmit_bytes_total{device!=\"lo\"}[1m])\r\n",
          "hide": false,
          "instant": false,
          "legendFormat": "전체",
          "range": true,
          "refId": "전"
        }
      ],
      "title": "🛜 네트워크 사용량",
      "transparent": true,
      "type": "timeseries"
    },
    {
      "datasource": {
        "type": "prometheus",
        "uid": "cekvp414w9e68e"
      },
      "fieldConfig": {
        "defaults": {
          "color": {
            "mode": "palette-classic"
          },
          "custom": {
            "axisBorderShow": false,
            "axisCenteredZero": false,
            "axisColorMode": "text",
            "axisLabel": "",
            "axisPlacement": "auto",
            "barAlignment": 0,
            "barWidthFactor": 0.6,
            "drawStyle": "line",
            "fillOpacity": 0,
            "gradientMode": "none",
            "hideFrom": {
              "legend": false,
              "tooltip": false,
              "viz": false
            },
            "insertNulls": false,
            "lineInterpolation": "linear",
            "lineWidth": 1,
            "pointSize": 5,
            "scaleDistribution": {
              "type": "linear"
            },
            "showPoints": "auto",
            "spanNulls": false,
            "stacking": {
              "group": "A",
              "mode": "none"
            },
            "thresholdsStyle": {
              "mode": "off"
            }
          },
          "mappings": [],
          "thresholds": {
            "mode": "absolute",
            "steps": [
              {
                "color": "green"
              },
              {
                "color": "red",
                "value": 80
              }
            ]
          }
        },
        "overrides": []
      },
      "gridPos": {
        "h": 8,
        "w": 12,
        "x": 12,
        "y": 15
      },
      "id": 5,
      "options": {
        "legend": {
          "calcs": [],
          "displayMode": "list",
          "placement": "bottom",
          "showLegend": false
        },
        "tooltip": {
          "hideZeros": false,
          "mode": "single",
          "sort": "none"
        }
      },
      "pluginVersion": "11.6.0",
      "targets": [
        {
          "datasource": {
            "type": "prometheus",
            "uid": "cekvp414w9e68e"
          },
          "editorMode": "code",
          "expr": "rate(promhttp_metric_handler_errors_total[5m])\r\n",
          "hide": false,
          "instant": false,
          "legendFormat": "__auto",
          "range": true,
          "refId": "A"
        }
      ],
      "title": "⚠️ 원인별 오류",
      "transparent": true,
      "type": "timeseries"
    }
  ],
  "preload": false,
  "schemaVersion": 41,
  "tags": [],
  "templating": {
    "list": []
  },
  "time": {
    "from": "now-5m",
    "to": "now"
  },
  "timepicker": {},
  "timezone": "browser",
  "title": "streaming server monitoring dashboard",
  "uid": "cekvqhimr0lj4a",
  "version": 21
}